adafruit_circuitpython_ra8875-3.1.27.dist-info/licenses/LICENSE
adafruit_ra8875/__init__.py
adafruit_ra8875/ra8875.py
adafruit_ra8875/registers.py
adafruit_circuitpython_ra8875-3.1.27.dist-info/METADATA
adafruit_circuitpython_ra8875-3.1.27.dist-info/WHEEL
adafruit_circuitpython_ra8875-3.1.27.dist-info/top_level.txt
adafruit_circuitpython_ra8875-3.1.27.dist-info/RECORD
